dynamiqs/__init__.py
dynamiqs/_checks.py
dynamiqs/_utils.py
dynamiqs/conftest.py
dynamiqs/gradient.py
dynamiqs/helpers.py
dynamiqs/hermitian_conjugate.py
dynamiqs/method.py
dynamiqs/options.py
dynamiqs/progress_meter.py
dynamiqs/result.py
dynamiqs/stochastic_helpers.py
dynamiqs/time_qarray.py
dynamiqs/integrators/__init__.py
dynamiqs/integrators/_utils.py
dynamiqs/integrators/apis/__init__.py
dynamiqs/integrators/apis/dsmesolve.py
dynamiqs/integrators/apis/dssesolve.py
dynamiqs/integrators/apis/floquet.py
dynamiqs/integrators/apis/jsmesolve.py
dynamiqs/integrators/apis/jssesolve.py
dynamiqs/integrators/apis/mepropagator.py
dynamiqs/integrators/apis/mesolve.py
dynamiqs/integrators/apis/sepropagator.py
dynamiqs/integrators/apis/sesolve.py
dynamiqs/integrators/core/__init__.py
dynamiqs/integrators/core/abstract_integrator.py
dynamiqs/integrators/core/diffrax_integrator.py
dynamiqs/integrators/core/event_integrator.py
dynamiqs/integrators/core/expm_integrator.py
dynamiqs/integrators/core/fixed_step_stochastic_integrator.py
dynamiqs/integrators/core/floquet_integrator.py
dynamiqs/integrators/core/interfaces.py
dynamiqs/integrators/core/montecarlo_integrator.py
dynamiqs/integrators/core/rouchon_integrator.py
dynamiqs/integrators/core/save_mixin.py
dynamiqs/plot/__init__.py
dynamiqs/plot/colormaps.py
dynamiqs/plot/fock.py
dynamiqs/plot/hinton.py
dynamiqs/plot/misc.py
dynamiqs/plot/qubit.py
dynamiqs/plot/utils.py
dynamiqs/plot/wigner.py
dynamiqs/qarrays/__init__.py
dynamiqs/qarrays/dense_qarray.py
dynamiqs/qarrays/layout.py
dynamiqs/qarrays/qarray.py
dynamiqs/qarrays/sparsedia_primitives.py
dynamiqs/qarrays/sparsedia_qarray.py
dynamiqs/qarrays/utils.py
dynamiqs/random/__init__.py
dynamiqs/random/core.py
dynamiqs/utils/__init__.py
dynamiqs/utils/general.py
dynamiqs/utils/global_settings.py
dynamiqs/utils/operators.py
dynamiqs/utils/optimal_control.py
dynamiqs/utils/states.py
dynamiqs/utils/vectorization.py
dynamiqs/utils/wigner_utils.py
dynamiqs-0.3.4.dist-info/licenses/LICENSE
dynamiqs-0.3.4.dist-info/WHEEL
dynamiqs-0.3.4.dist-info/METADATA
dynamiqs-0.3.4.dist-info/RECORD
