Metadata-Version: 2.4
Name: dynamiqs
Version: 0.3.4
Summary: High-performance quantum systems simulation with JAX (GPU-accelerated & differentiable solvers).
Author-email: Pierre Guilmin <pierreguilmin@gmail.com>, Ronan Gautier <ron.gautier@gmail.com>, Adrien Bocquet <adrienbocquet38@gmail.com>, Elie Genois <elie.genois@usherbrooke.ca>, Daniel Weiss <daniel.kamrath.weiss@gmail.com>
Requires-Python: >=3.10
Classifier: License :: OSI Approved :: Apache Software License
Classifier: Operating System :: OS Independent
Classifier: Programming Language :: Python :: 3
Classifier: Topic :: Scientific/Engineering :: Physics
License-File: LICENSE
Requires-Dist: qutip>=4.7.5
Requires-Dist: scipy
Requires-Dist: numpy
Requires-Dist: matplotlib
Requires-Dist: tqdm
Requires-Dist: jax>=0.4.36,<0.7
Requires-Dist: jaxtyping
Requires-Dist: diffrax>=0.6.1
Requires-Dist: equinox
Requires-Dist: optimistix
Requires-Dist: pillow
Requires-Dist: cmap
Requires-Dist: ipython
Requires-Dist: tqdm
Requires-Dist: taskipy ; extra == "dev"
Requires-Dist: ruff>=0.8 ; extra == "dev"
Requires-Dist: codespell ; extra == "dev"
Requires-Dist: pytest>=8.0 ; extra == "dev"
Requires-Dist: pytest-ordering ; extra == "dev"
Requires-Dist: pytest-sugar ; extra == "dev"
Requires-Dist: pytest-xdist ; extra == "dev"
Requires-Dist: mkdocs-material ; extra == "dev"
Requires-Dist: mkdocstrings[python]!=1.12.0 ; extra == "dev"
Requires-Dist: mkdocs-gen-files ; extra == "dev"
Requires-Dist: mkdocs-literate-nav ; extra == "dev"
Requires-Dist: mkdocs-section-index ; extra == "dev"
Requires-Dist: mkdocs-simple-hooks ; extra == "dev"
Requires-Dist: mkdocs-glightbox ; extra == "dev"
Requires-Dist: mkdocs-exclude ; extra == "dev"
Requires-Dist: sybil>=6 ; extra == "dev"
Requires-Dist: black ; extra == "dev"
Requires-Dist: flit ; extra == "dev"
Requires-Dist: mike ; extra == "dev"
Requires-Dist: optax ; extra == "dev"
Project-URL: Documentation, https://www.dynamiqs.org/
Project-URL: Homepage, https://github.com/dynamiqs/dynamiqs
Project-URL: Repository, https://github.com/dynamiqs/dynamiqs
Provides-Extra: dev
